maekrak/__init__.py
maekrak/ai/__init__.py
maekrak/ai/clustering_service.py
maekrak/ai/embedding_service.py
maekrak/ai/model_manager.py
maekrak/ai/vector_search.py
maekrak/cli.py
maekrak/core/__init__.py
maekrak/core/file_processor.py
maekrak/core/log_parsers.py
maekrak/core/maekrak_engine.py
maekrak/core/search_engine.py
maekrak/core/trace_analyzer.py
maekrak/data/__init__.py
maekrak/data/database.py
maekrak/data/migrations.py
maekrak/data/models.py
maekrak/data/repositories.py
maekrak/utils/__init__.py
maekrak/utils/progress.py
maekrak/utils/time_utils.py
maekrak-0.1.3.dist-info/METADATA
maekrak-0.1.3.dist-info/WHEEL
maekrak-0.1.3.dist-info/entry_points.txt
maekrak-0.1.3.dist-info/RECORD
