Metadata-Version: 2.4
Name: maekrak
Version: 0.1.3
Summary: AI-powered log analyzer for local environments
Author: JINWOO
Author-email: lkasa5546@gmail.com
Requires-Python: >=3.8,<4.0
Classifier: Programming Language :: Python :: 3
Classifier: Programming Language :: Python :: 3.8
Classifier: Programming Language :: Python :: 3.9
Classifier: Programming Language :: Python :: 3.10
Classifier: Programming Language :: Python :: 3.11
Classifier: Programming Language :: Python :: 3.12
Classifier: Programming Language :: Python :: 3.13
Classifier: Programming Language :: Python :: 3.14
Requires-Dist: click (>=8.1.0,<9.0.0)
Requires-Dist: faiss-cpu (>=1.7.0,<2.0.0)
Requires-Dist: hdbscan (>=0.8.0,<0.9.0)
Requires-Dist: numpy (>=1.24.0,<2.0.0)
Requires-Dist: pandas (>=2.0.0,<3.0.0)
Requires-Dist: pyyaml (>=6.0,<7.0)
Requires-Dist: rich (>=13.0.0,<14.0.0)
Requires-Dist: scikit-learn (>=1.3.0,<2.0.0)
Requires-Dist: sentence-transformers (>=2.2.0,<3.0.0)
Requires-Dist: toml (>=0.10.0,<0.11.0)
Requires-Dist: tqdm (>=4.65.0,<5.0.0)
